soracom_sandbox/__init__.py
soracom_sandbox/api/__init__.py
soracom_sandbox/api/coupon_api.py
soracom_sandbox/api/operator_api.py
soracom_sandbox/api/order_api.py
soracom_sandbox/api/stats_api.py
soracom_sandbox/api/subscriber_api.py
soracom_sandbox/api_client.py
soracom_sandbox/apis/__init__.py
soracom_sandbox/configuration.py
soracom_sandbox/exceptions.py
soracom_sandbox/model/__init__.py
soracom_sandbox/model/sandbox_auth_response.py
soracom_sandbox/model/sandbox_beam_counts.py
soracom_sandbox/model/sandbox_create_coupon_request.py
soracom_sandbox/model/sandbox_create_coupon_response.py
soracom_sandbox/model/sandbox_create_subscriber_request.py
soracom_sandbox/model/sandbox_create_subscriber_response.py
soracom_sandbox/model/sandbox_data_traffic_stats.py
soracom_sandbox/model/sandbox_get_signup_token_request.py
soracom_sandbox/model/sandbox_get_signup_token_response.py
soracom_sandbox/model/sandbox_init_request.py
soracom_sandbox/model/sandbox_insert_air_stats_request.py
soracom_sandbox/model/sandbox_insert_air_stats_request_data_traffic_stats_map.py
soracom_sandbox/model/sandbox_insert_beam_stats_request.py
soracom_sandbox/model/sandbox_insert_beam_stats_request_beam_stats_map.py
soracom_sandbox/model/sandbox_ship_order_request.py
soracom_sandbox/model/tag_set.py
soracom_sandbox/model_utils.py
soracom_sandbox/models/__init__.py
soracom_sandbox/rest.py
soracom_sandbox-0.0.1.dist-info/WHEEL
soracom_sandbox-0.0.1.dist-info/METADATA
soracom_sandbox-0.0.1.dist-info/RECORD
