Metadata-Version: 2.1
Name: soracom-sandbox
Version: 0.0.1
Summary: SORACOM SANDBOX API Client for the Python programming language based on the OpenAPI specification
License: MIT
Author: ks6088ts
Author-email: ks6088ts@gmail.com
Requires-Python: >=3.6,<4.0
Classifier: License :: OSI Approved :: MIT License
Classifier: Programming Language :: Python :: 3
Classifier: Programming Language :: Python :: 3.10
Classifier: Programming Language :: Python :: 3.6
Classifier: Programming Language :: Python :: 3.7
Classifier: Programming Language :: Python :: 3.8
Classifier: Programming Language :: Python :: 3.9
Requires-Dist: python-dateutil (>=2.8.2,<3.0.0)
Requires-Dist: urllib3 (>=1.26.9,<2.0.0)
